jinja_comprehensions/__init__.py
jinja_comprehensions/compiler.py
jinja_comprehensions/environment.py
jinja_comprehensions/nativetypes.py
jinja_comprehensions/nodes.py
jinja_comprehensions/parser.py
jinja_comprehensions/runtime.py
jinja_comprehensions/util.py
jinja_comprehensions-0.1.1.dist-info/LICENSE
jinja_comprehensions-0.1.1.dist-info/METADATA
jinja_comprehensions-0.1.1.dist-info/WHEEL
jinja_comprehensions-0.1.1.dist-info/RECORD
